{"SerializedFilePath":"C:\\Users\\gs_gr\\OneDrive\\Masa端st端\\Calisma-Masasi\\BlazorV2\\Tangy\\TangyWeb_Client\\obj\\Debug\\net6.0\\project.razor.json","FilePath":"C:\\Users\\gs_gr\\OneDrive\\Masa端st端\\Calisma-Masasi\\BlazorV2\\Tangy\\TangyWeb_Client\\TangyWeb_Client.csproj","Configuration":{"ConfigurationName":"Default","LanguageVersion":"6.0","Extensions":[]},"ProjectWorkspaceState":{"TagHelpers":[],"CSharpLanguageVersion":1000},"RootNamespace":"TangyWeb_Client","Documents":[],"SerializationFormat":"0.3"}